{
    "name": "VI",
    "website": "https://vid.camera/",
    "description": "Forked from Ethereum with Pulsechain. VI is the native token used in the Vid app. Vid is a social media platform that pays you for the value you provide to the platform.",
    "explorer": "https://scan.pulsechain.com/token/0x8b6c3b7C01D9dB4393f9aa734750F36df1543E9A",
    "type": "PRC20",
    "symbol": "VI",
    "decimals": 18,
    "status": "active",
    "id": "0x8b6c3b7C01D9dB4393f9aa734750F36df1543E9A",
    "links": [
        {
            "name": "whitepaper",
            "url": "https://vid.camera/files/Vi-UBI.pdf"
        }
    ],
    "chain": 369
}